{"id":1598,"idMal":1598,"title":{"romaji":"Casshern","english":"Casshan: Robot Hunter","native":"キャシャーン"},"type":"ANIME","format":"OVA","status":"FINISHED","description":"In the near future, robot technology has advanced to the point of self-awareness. Under the leadership of the \"Black King,\" machines have decimated the human population and conquered the world. Those who survived the early holocaust have been enslaved for life. But throughout the hardships, a lone hero appears as the savior of mankind. He is Casshan - a fusion of man and machine driven to combat Black King and his forces to the end.\n<br><br>\n(Source: Anime News Network)","startDate":{"year":1993,"month":8,"day":21},"endDate":{"year":1994,"month":2,"day":21},"season":"SUMMER","seasonYear":1993,"episodes":4,"duration":27,"chapters":null,"volumes":null,"countryOfOrigin":"JP","source":null,"coverImage":{"extraLarge":"https://s4.anilist.co/file/anilistcdn/media/anime/cover/large/nx1598-2p6wAuyMHN7z.jpg","large":"https://s4.anilist.co/file/anilistcdn/media/anime/cover/medium/nx1598-2p6wAuyMHN7z.jpg","medium":"https://s4.anilist.co/file/anilistcdn/media/anime/cover/small/nx1598-2p6wAuyMHN7z.jpg"},"bannerImage":"https://s4.anilist.co/file/anilistcdn/media/anime/banner/n1598-dCIGIhK0aHuR.jpg","genres":["Adventure","Mecha","Sci-Fi"],"averageScore":59,"popularity":2940,"relations":{"edges":[{"relationType":"ALTERNATIVE","node":{"id":4810,"title":{"romaji":"Shinzou Ningen Casshern"},"type":"ANIME"}},{"relationType":"ALTERNATIVE","node":{"id":4981,"title":{"romaji":"Casshern Sins"},"type":"ANIME"}},{"relationType":"ALTERNATIVE","node":{"id":168408,"title":{"romaji":"Casshern R"},"type":"MANGA"}}]}}
