{"id":557,"idMal":557,"title":{"romaji":"Koutetsu Tenshi Kurumi: DVD Single Episodes","english":"Steel Angel Kurumi Encore","native":"鋼鉄天使くるみ DVDシングル エピソード"},"type":"ANIME","format":"OVA","status":"FINISHED","description":"Four additional short stories of the Steel Angels: Saki becomes a film actress, Karinka goes on a blind date with Kamihito, Kurumi practices the art of becoming a traditional Japanese woman, and the rest of the Steel Angels engage in a contest to win Nakahito's heart.\n<br><br>\n(Source: Anime News Network)","startDate":{"year":2000,"month":7,"day":19},"endDate":{"year":2000,"month":10,"day":4},"season":"SUMMER","seasonYear":2000,"episodes":4,"duration":15,"chapters":null,"volumes":null,"countryOfOrigin":"JP","source":"ORIGINAL","coverImage":{"extraLarge":"https://s4.anilist.co/file/anilistcdn/media/anime/cover/medium/557.jpg","large":"https://s4.anilist.co/file/anilistcdn/media/anime/cover/medium/557.jpg","medium":"https://s4.anilist.co/file/anilistcdn/media/anime/cover/small/557.jpg"},"bannerImage":null,"genres":["Comedy","Romance","Sci-Fi"],"averageScore":63,"popularity":1536,"relations":{"edges":[{"relationType":"PARENT","node":{"id":554,"title":{"romaji":"Koutetsu Tenshi Kurumi"},"type":"ANIME"}}]}}
