{"id":54,"idMal":54,"title":{"romaji":"Appleseed (Movie)","english":"Appleseed (Movie)","native":"アップルシード"},"type":"ANIME","format":"MOVIE","status":"FINISHED","description":"Growing out of the chaos of a global war, the city of Utopia is populated by humans and bioroids (artificial humans). On the surface, everything is harmonious, but tensions lurk. Into this seemingly perfect society comes a survivor of the wars, Deunan Knute, who carries a legacy that will turn out to be of critical importance to the future of humanity. <br><br>\n(Source: Anime News Network)","startDate":{"year":2004,"month":4,"day":17},"endDate":{"year":2004,"month":4,"day":17},"season":"SPRING","seasonYear":2004,"episodes":1,"duration":105,"chapters":null,"volumes":null,"countryOfOrigin":"JP","source":"MANGA","coverImage":{"extraLarge":"https://s4.anilist.co/file/anilistcdn/media/anime/cover/large/bx54-NRZifY4de4u4.jpg","large":"https://s4.anilist.co/file/anilistcdn/media/anime/cover/medium/bx54-NRZifY4de4u4.jpg","medium":"https://s4.anilist.co/file/anilistcdn/media/anime/cover/small/bx54-NRZifY4de4u4.jpg"},"bannerImage":null,"genres":["Action","Drama","Mecha","Sci-Fi"],"averageScore":65,"popularity":10406,"relations":{"edges":[{"relationType":"SEQUEL","node":{"id":2969,"title":{"romaji":"Appleseed Saga Ex Machina"},"type":"ANIME"}},{"relationType":"ALTERNATIVE","node":{"id":937,"title":{"romaji":"Appleseed"},"type":"ANIME"}},{"relationType":"PREQUEL","node":{"id":20786,"title":{"romaji":"Appleseed α"},"type":"ANIME"}},{"relationType":"ALTERNATIVE","node":{"id":9737,"title":{"romaji":"Appleseed XIII"},"type":"ANIME"}},{"relationType":"ADAPTATION","node":{"id":30668,"title":{"romaji":"Appleseed"},"type":"MANGA"}}]}}
