{"id":25,"idMal":25,"title":{"romaji":"Sunabouzu","english":"Desert Punk","native":"砂ぼうず"},"type":"ANIME","format":"TV","status":"FINISHED","description":"The Great Kanto Desert is a miserable place. It’s also the home of hero-for-hire Desert Punk, the closest thing to a good guy the wasteland’s got. He’s known as the best man for any job, but his reputation is undone by his raging hormones when curvy Junko uses her double-D charms to double-cross him. With debt hanging over his head, Desert Punk sets out to salvage his name. <br><br>\n(Source: Crunchyroll)","startDate":{"year":2004,"month":10,"day":6},"endDate":{"year":2005,"month":3,"day":30},"season":"FALL","seasonYear":2004,"episodes":24,"duration":24,"chapters":null,"volumes":null,"countryOfOrigin":"JP","source":"MANGA","coverImage":{"extraLarge":"https://s4.anilist.co/file/anilistcdn/media/anime/cover/large/bx25-H1etX7IgfFtQ.jpg","large":"https://s4.anilist.co/file/anilistcdn/media/anime/cover/medium/bx25-H1etX7IgfFtQ.jpg","medium":"https://s4.anilist.co/file/anilistcdn/media/anime/cover/small/bx25-H1etX7IgfFtQ.jpg"},"bannerImage":"https://s4.anilist.co/file/anilistcdn/media/anime/banner/25-F2qEJ3hvFzHj.jpg","genres":["Action","Adventure","Comedy","Ecchi","Sci-Fi"],"averageScore":68,"popularity":27041,"relations":{"edges":[{"relationType":"ADAPTATION","node":{"id":40016,"title":{"romaji":"Sunabouzu"},"type":"MANGA"}}]}}
